pipettor/__init__.py
pipettor/devices.py
pipettor/docstrings.py
pipettor/exceptions.py
pipettor/processes.py
pipettor-1.2.1.dist-info/licenses/AUTHORS.rst
pipettor-1.2.1.dist-info/licenses/LICENSE.txt
pipettor-1.2.1.dist-info/METADATA
pipettor-1.2.1.dist-info/WHEEL
pipettor-1.2.1.dist-info/top_level.txt
pipettor-1.2.1.dist-info/zip-safe
pipettor-1.2.1.dist-info/RECORD
